cmdcolorprint/__init__.py
cmdcolorprint/color_print.py
color_print/__init__.py
color_print/color_print.py
colorprint/__init__.py
colorprint/color_print.py
cprint/__init__.py
cprint/color_print.py
cmdcolorprint-1.1.1.dist-info/METADATA
cmdcolorprint-1.1.1.dist-info/WHEEL
cmdcolorprint-1.1.1.dist-info/entry_points.txt
cmdcolorprint-1.1.1.dist-info/top_level.txt
cmdcolorprint-1.1.1.dist-info/RECORD
