Metadata-Version: 2.1
Name: cmdcolorprint
Version: 1.1.1
Summary: cmd color print
Home-page: https://github.com/hashibutogarasu/cmdcolorprint
Author: Columba_Karasu
License: UNKNOWN
Platform: UNKNOWN
Classifier: Programming Language :: Python :: 3
Classifier: License :: OSI Approved :: MIT License
Classifier: Operating System :: OS Independent
Requires-Python: >=3.9.5
